{"number": "平成十二年六月七日政令第三百十四号", "name": "中央省庁等改革に伴い関係政令等を廃止する政令", "provision": {"附則 １": {"text": "１\n　この政令は、動物の保護及び管理に関する法律の一部を改正する法律の施行の日（平成十二年十二月一日）から施行する。"}, "附則 ２": {"text": "２\n　この政令の施行の日の前日において次に掲げる従前の審議会等の委員その他の職員である者（任期の定めのない者を除く。）の任期は、当該委員その他の職員の任期を定めたそれぞれの政令の規定にかかわらず、その日に満了する。\n一\n　労働者災害補償保険審議会\n\n二\n　民事行政審議会\n\n三\n　厚生統計協議会\n\n四\n　郵政審議会\n\n五\n　女性少年問題審議会\n\n六\n　保健体育審議会\n\n七\n　測地学審議会\n\n八\n　身体障害者福祉審議会\n\n九\n　国語審議会\n\n十\n　教育課程審議会\n\n十一\n　教育職員養成審議会\n\n十二\n　農業資材審議会\n\n十三\n　あん摩、マツサージ、指圧、はり、きゆう、柔道整復等審議会\n\n十四\n　工業所有権審議会\n\n十五\n　米価審議会\n\n十六\n　かんがい排水審議会\n\n十七\n　中央教育審議会\n\n十八\n　経済審議会\n\n十九\n　海運造船合理化審議会\n\n二十\n　航空審議会\n\n二十一\n　人口問題審議会\n\n二十二\n　農業機械化審議会\n\n二十三\n　港湾審議会\n\n二十四\n　医道審議会\n\n二十五\n　資源調査会\n\n二十六\n　中小企業退職金共済審議会\n\n二十七\n　中央生乳取引調停審議会\n\n二十八\n　中央薬事審議会\n\n二十九\n　海洋開発審議会\n\n三十\n　対外経済協力審議会\n\n三十一\n　鉱業審議会\n\n三十二\n　貿易会議\n\n三十三\n　車両競技審議会\n\n三十四\n　観光政策審議会\n\n三十五\n　中央社会福祉審議会\n\n三十六\n　中小企業政策審議会\n\n三十七\n　産業構造審議会\n\n三十八\n　沿岸漁業等振興審議会\n\n三十九\n　港湾調整審議会\n\n四十\n　生活環境審議会\n\n四十一\n　建築審議会\n\n四十二\n　高圧ガス及び火薬類保安審議会\n\n四十三\n　理科教育及び産業教育審議会\n\n四十四\n　畜産振興審議会\n\n四十五\n　工場立地及び工業用水審議会\n\n四十六\n　弁理士審査会\n\n四十七\n　矯正保護審議会\n\n四十八\n　学術審議会\n\n四十九\n　文化財保護審議会\n\n五十\n　住宅宅地審議会\n\n五十一\n　都市計画中央審議会\n\n五十二\n　臨時大学問題審議会\n\n五十三\n　医療関係者審議会\n\n五十四\n　運輸政策審議会\n\n五十五\n　運輸技術審議会\n\n五十六\n　海上安全船員教育審議会\n\n五十七\n　情報処理振興審議会\n\n五十八\n　繊維産業審議会\n\n五十九\n　中央障害者施策推進協議会\n\n六十\n　著作権審議会\n\n六十一\n　勤労者財産形成審議会\n\n六十二\n　自然環境保全審議会\n\n六十三\n　産業技術審議会\n\n六十四\n　自衛隊離職者就職審査会\n\n六十五\n　瀬戸内海環境保全審議会\n\n六十六\n　国民生活安定審議会\n\n六十七\n　航空・電子等技術審議会\n\n六十八\n　公衆衛生審議会\n\n六十九\n　農林水産統計観測審議会\n\n七十\n　石油審議会\n\n七十一\n　電気通信審議会\n\n七十二\n　たばこ事業等審議会\n\n七十三\n　電気通信技術審議会\n\n七十四\n　年金審議会\n\n七十五\n　航空機工業審議会\n\n七十六\n　新幹線鉄道審議会\n\n七十七\n　大学審議会\n\n七十八\n　生涯学習審議会\n\n七十九\n　食品流通審議会\n\n八十\n　厚生科学審議会\n\n八十一\n　医療保険福祉審議会"}}}