{"number": "昭和三十九年三月三十一日運輸省令第二十一号", "provision": {"第二条": {"text": "第二条\n　この省令の施行の際現にあるこの省令による改正前の様式又は書式による申請書その他の文書は、この省令による改正後のそれぞれの様式又は書式にかかわらず、当分の間、なおこれを使用することができる。"}, "第二条の二": {"２": {"text": "２\n\n　前項の輸送実績報告書は、前年四月一日から三月三十一日までの期間に係るものとする。"}, "text": "第二条の二\n\n　自家用有償旅客運送者は、自家用有償旅客運送に係る路線又は運送の区域が存する区域を管轄する運輸監理部長又は運輸支局長（当該区域が主として指定都道府県等（道路運送法施行令\n（昭和二十六年政令第二百五十号）第四条第一項\nの指定都道府県等をいう。以下同じ。）の区域内にある場合にあつては、当該指定都道府県等の長）に、自家用有償旅客運送の種別ごとに第六号様式による輸送実績報告書を、毎年五月三十一日までに一通提出しなければならない。"}, "第一条": {"text": "第一条\n　この省令は、平成二十七年四月一日から施行する。"}, "第四条": {"text": "第四条\n　平成二十六年四月一日から平成二十七年三月三十一日までの一年間に係る輸送実績報告書の様式については、なお従前の例によることができる。"}, "附則 ２": {"text": "２\n　この省令の施行の際現に貨物自動車運送事業法附則第十四条の規定による改正前の道路運送法（昭和二十六年法律第百八十三号）第三条第二項第四号及び第五号並びに第三項第二号に規定する事業について同法第四条第一項の免許又は同法第四十五条第一項の許可を受けている者の平成二年十一月三十日以前に開始する事業年度に係る第十条の規定による改正前の自動車運送事業等報告規則第二条第一項に規定する営業報告書及び平成二年度の輸送の実績に係る同令第三条第一項に規定する輸送実績報告書の提出については、なお従前の例による。"}, "附則 １": {"text": "１\n　この省令は、特定地域における一般乗用旅客自動車運送事業の適正化及び活性化に関する特別措置法等の一部を改正する法律の施行の日から施行する。"}, "第三条": {"text": "第三条\n　平成二十六年四月一日から平成二十七年三月三十一日までの一年間に係るこの省令による改正前の旅客自動車運送事業等報告規則第二条の二第一項に規定する輸送実績報告書の提出については、なお従前の例による。"}, "附則 ３": {"text": "３\n　平成二十五年四月一日から平成二十六年三月三十一日までの一年間に係るこの省令による改正前の旅客自動車運送事業等報告規則第二条第一項に規定する輸送実績報告書の提出については、なお従前の例による。"}}, "name": "旅客自動車運送事業等報告規則"}