{"number": "昭和六十二年二月二十日運輸省令第九号", "provision": {"第二条": {"text": "第二条\n　この省令の施行の際現にあるこの省令による改正前の様式又は書式による申請書その他の文書は、この省令による改正後のそれぞれの様式又は書式にかかわらず、当分の間、なおこれを使用することができる。"}, "第一条": {"text": "第一条\n　この省令は、運輸の安全性の向上のための鉄道事業法等の一部を改正する法律の施行の日から施行する。"}, "第四条": {"text": "第四条\n\n　この省令の規定により国土交通大臣に報告書を提出する場合には、所轄地方運輸局長を経由しなければならない。"}, "附則 ２": {"text": "２\n　昭和六十二年三月末日以前に終了した事業年度に係る業務又は経理の状況に関する報告については、なお従前の例による。"}, "附則 １": {"text": "１\n　この省令は、公布の日から施行する。"}, "第三条": {"text": "第三条\n　この省令の施行前にしたこの省令による改正前の省令の規定による処分、手続、その他の行為は、この省令による改正後の省令（以下「新令」という。）の規定の適用については、新令の相当規定によってしたものとみなす。"}}, "name": "鉄道事業等報告規則"}